echo_file.py
echo_file-0.0.2.dist-info/LICENSE
echo_file-0.0.2.dist-info/METADATA
echo_file-0.0.2.dist-info/WHEEL
echo_file-0.0.2.dist-info/top_level.txt
echo_file-0.0.2.dist-info/RECORD
