Metadata-Version: 2.1
Name: echo-file
Version: 0.0.2
Summary: Write text to file
Author: wangziling100
Author-email: wangziling100@163.com
Classifier: Programming Language :: Python :: 3
Classifier: License :: OSI Approved :: MIT License
License-File: LICENSE
